{
  "1": {
    "Uncategorized": 9944,
    "Communications": 11538,
    "Email": 4364,
    "Writing": 3287,
    "General Business": 5099,
    "Meetings": 8460,
    "Calendars": 3109,
    "General Other Work": 2858,
    "General Shopping": 1713,
    "Search": 2164,
    "General Reference & Learning": 1056,
    "Internet Utilities": 1255,
    "General Software Development": 4580,
    "General Entertainment": 410,
    "Browsers": 1062,
    "Project Management": 2906,
    "General Focus Work": 730,
    "Legal & Gov't": 319,
    "General Social Networking": 3908,
    "General News & Opinion": 1814,
    "Science & Technology": 242,
    "General Personal": 3067,
    "Intelligence": 687,
    "Regional": 27,
    "Instant Message": 27,
    "Editing & IDEs": 11945,
    "Accounting": 2,
    "Electronics": 1,
    "General Communication & Scheduling": 4,
    "General Utilities": 101,
    "Video": 685,
    "Clothes & Personal": 168,
    "Engineering & Drafting": 17,
    "Presentation": 647,
    "Engineering & Technology": 163,
    "Games": 12
  },
  "2": {},
  "3": {},
  "4": {},
  "5": {},
  "6": {},
  "7": {},
  "8": {},
  "9": {},
  "10": {},
  "11": {},
  "12": {}
}