{
  "2023-01-1": {},
  "2023-01-2": {
    "Uncategorized": 4775,
    "Communications": 3702,
    "Email": 1967,
    "Writing": 1709,
    "General Business": 1079,
    "Meetings": 1047,
    "Calendars": 990,
    "General Other Work": 983,
    "General Shopping": 846,
    "Search": 822,
    "General Reference & Learning": 777,
    "Internet Utilities": 574,
    "General Software Development": 416,
    "General Entertainment": 410,
    "Browsers": 388,
    "Project Management": 364,
    "General Focus Work": 362,
    "Legal & Gov't": 319,
    "General Social Networking": 292,
    "General News & Opinion": 187,
    "Science & Technology": 125,
    "General Personal": 124,
    "Intelligence": 57,
    "Regional": 27,
    "Instant Message": 20,
    "Editing & IDEs": 12,
    "Accounting": 2,
    "General Utilities": 1,
    "Electronics": 1,
    "General Communication & Scheduling": 1
  },
  "2023-01-3": {},
  "2023-01-4": {},
  "2023-01-5": {},
  "2023-01-6": {},
  "2023-01-7": {}
}