{
  "2022": {
    "Entertainment": 2500,
    "Uncategorized": 15809,
    "Focus Work": 34351,
    "Utilities": 10268,
    "Software Development": 64409,
    "Reference & Learning": 7023,
    "Communication & Scheduling": 35468,
    "Business": 12762,
    "Shopping": 6445,
    "News & Opinion": 2841,
    "Design & Composition": 17880,
    "Social Networking": 6296,
    "Personal": 8826,
    "Other Work": 24520
  },
  "2023": {
    "Uncategorized": 290788,
    "Communication & Scheduling": 236375,
    "Other Work": 276642,
    "Reference & Learning": 92287,
    "Design & Composition": 84698,
    "Business": 170570,
    "Utilities": 90056,
    "Personal": 79275,
    "Shopping": 12808,
    "Software Development": 906022,
    "Entertainment": 39413,
    "Focus Work": 24640,
    "News & Opinion": 15291,
    "Social Networking": 77648
  }
}